{
  "name" : "A. Grid game",
  "testType" : "SINGLE",
  "input" : {
    "type" : "STANDARD",
    "fileName" : "input.txt"
  },
  "output" : {
    "type" : "STANDARD",
    "fileName" : "output.txt"
  },
  "tests" : [ {
    "input" : "010\n",
    "output" : "1 1\n1 2\n1 4\n",
    "index" : 0,
    "active" : true
  }, {
    "input" : "000000000000000000",
    "index" : 1,
    "active" : true
  } ],
  "location" : "src/main",
  "vmArgs" : "-Xmx256M",
  "mainClass" : "Main",
  "taskClass" : "main.AGridGame",
  "checkerClass" : "net.egork.chelper.checkers.TokenChecker",
  "checkerParameters" : "",
  "testClasses" : [ ],
  "date" : "2019.01.23",
  "contestName" : "Codeforces Round #534 (Div. 1)",
  "truncate" : true,
  "inputClass" : "fastio.InputReader",
  "outputClass" : "fastio.OutputWriter",
  "includeLocale" : false,
  "failOnOverflow" : false,
  "interactive" : false,
  "interactor" : "net.egork.chelper.tester.Interactor"
}